unique_stock_ticker/__init__.py
unique_stock_ticker/clients/six/__init__.py
unique_stock_ticker/clients/six/client.py
unique_stock_ticker/clients/six/exception.py
unique_stock_ticker/clients/six/get_creds.sh
unique_stock_ticker/clients/six/http_adapter.py
unique_stock_ticker/clients/six/schema/__init__.py
unique_stock_ticker/clients/six/schema/common/base/__init__.py
unique_stock_ticker/clients/six/schema/common/base/model.py
unique_stock_ticker/clients/six/schema/common/base/request.py
unique_stock_ticker/clients/six/schema/common/base/response.py
unique_stock_ticker/clients/six/schema/common/entity.py
unique_stock_ticker/clients/six/schema/common/instrument.py
unique_stock_ticker/clients/six/schema/common/language.py
unique_stock_ticker/clients/six/schema/common/listing.py
unique_stock_ticker/clients/six/schema/common/lookup.py
unique_stock_ticker/clients/six/schema/common/market.py
unique_stock_ticker/clients/six/schema/common/price.py
unique_stock_ticker/clients/six/schema/common/security.py
unique_stock_ticker/clients/six/schema/end_of_day_history/__init__.py
unique_stock_ticker/clients/six/schema/end_of_day_history/request.py
unique_stock_ticker/clients/six/schema/end_of_day_history/response.py
unique_stock_ticker/clients/six/schema/entity_base/__init__.py
unique_stock_ticker/clients/six/schema/entity_base/listing/request.py
unique_stock_ticker/clients/six/schema/entity_base/listing/response.py
unique_stock_ticker/clients/six/schema/free_text_search/__init__.py
unique_stock_ticker/clients/six/schema/free_text_search/entities/__init__.py
unique_stock_ticker/clients/six/schema/free_text_search/entities/request.py
unique_stock_ticker/clients/six/schema/free_text_search/entities/response.py
unique_stock_ticker/clients/six/schema/free_text_search/instruments/__init__.py
unique_stock_ticker/clients/six/schema/free_text_search/instruments/request.py
unique_stock_ticker/clients/six/schema/free_text_search/instruments/response.py
unique_stock_ticker-1.0.2.dist-info/LICENSE
unique_stock_ticker-1.0.2.dist-info/METADATA
unique_stock_ticker-1.0.2.dist-info/WHEEL
unique_stock_ticker-1.0.2.dist-info/RECORD
