Metadata-Version: 2.3
Name: unique_stock_ticker
Version: 1.0.2
Summary: 
License: Proprietary
Author: Martin Fadler
Author-email: martin.fadler@unique.ch
Requires-Python: >=3.12,<4.0
Classifier: License :: Other/Proprietary License
Classifier: Programming Language :: Python :: 3
Classifier: Programming Language :: Python :: 3.12
Classifier: Programming Language :: Python :: 3.13
Requires-Dist: cryptography (>=45.0.6,<46.0.0)
Requires-Dist: numerize (>=0.12,<0.13)
Requires-Dist: plotly (>=5.24.1,<6.0.0)
Requires-Dist: pydantic (>=2.8.2,<3.0.0)
Requires-Dist: pydantic-settings (>=2.10.1,<3.0.0)
Requires-Dist: pyopenssl (>=25.1.0,<26.0.0)
Requires-Dist: pytest (>=8.4.1,<9.0.0)
Requires-Dist: python-dotenv (>=1.0.1,<2.0.0)
Requires-Dist: typing-extensions (>=4.9.0,<5.0.0)
Requires-Dist: unique-sdk (>=0.10.0,<0.11.0)
Requires-Dist: unique-toolkit (>=1.14.5,<2.0.0)
